Workbook

Sheet Assumptions
A1: Parameter | B1: Value | C1: Note
A2: Fund size | B2: 150000000 | C2: Total committed capital
A3: Mgmt Fee Yr1-5 | B3: 0.02 | C3: of committed
A4: Mgmt Fee Yr6-10 | B4: 0.015 | C4: step-down
A5: Carry | B5: 0.2 | C5: of profits over capital
A6: Investment period | B6: 5 | C6: years
A7: Fund life | B7: 10 | C7: years
A8: Reserve ratio | B8: 0.4 | C8: follow-ons
A9: Portfolio companies | B9: 30
A10: Target MOIC | B10: 2.8
A11: Target IRR | B11: 0.2

Sheet Capital Calls & Fees
A1: Year | B1: Capital Called | C1: Mgmt Fee | D1: Net Invested | E1: Cumulative Capital
A2: 1 | B2: =Assumptions!B1/5 | C2: =IF(A2<=5,Assumptions!B2,Assumptions!B3)*Assumptions!B1 | D2: =B2-C2 | E2: =SUM($B$2:B2)
A3: 2 | B3: =Assumptions!B1/5 | C3: =IF(A3<=5,Assumptions!B2,Assumptions!B3)*Assumptions!B1 | D3: =B3-C3 | E3: =SUM($B$2:B3)
A4: 3 | B4: =Assumptions!B1/5 | C4: =IF(A4<=5,Assumptions!B2,Assumptions!B3)*Assumptions!B1 | D4: =B4-C4 | E4: =SUM($B$2:B4)
A5: 4 | B5: =Assumptions!B1/5 | C5: =IF(A5<=5,Assumptions!B2,Assumptions!B3)*Assumptions!B1 | D5: =B5-C5 | E5: =SUM($B$2:B5)
A6: 5 | B6: =Assumptions!B1/5 | C6: =IF(A6<=5,Assumptions!B2,Assumptions!B3)*Assumptions!B1 | D6: =B6-C6 | E6: =SUM($B$2:B6)
A7: 6 | B7: 0 | C7: =IF(A7<=5,Assumptions!B2,Assumptions!B3)*Assumptions!B1 | D7: =B7-C7 | E7: =SUM($B$2:B7)
A8: 7 | B8: 0 | C8: =IF(A8<=5,Assumptions!B2,Assumptions!B3)*Assumptions!B1 | D8: =B8-C8 | E8: =SUM($B$2:B8)
A9: 8 | B9: 0 | C9: =IF(A9<=5,Assumptions!B2,Assumptions!B3)*Assumptions!B1 | D9: =B9-C9 | E9: =SUM($B$2:B9)
A10: 9 | B10: 0 | C10: =IF(A10<=5,Assumptions!B2,Assumptions!B3)*Assumptions!B1 | D10: =B10-C10 | E10: =SUM($B$2:B10)
A11: 10 | B11: 0 | C11: =IF(A11<=5,Assumptions!B2,Assumptions!B3)*Assumptions!B1 | D11: =B11-C11 | E11: =SUM($B$2:B11)

Sheet Distributions & Carry
A1: Year | B1: Gross Proceeds | C1: Gain | D1: Carry (20%) | E1: LP Distribution | F1: GP Distribution | G1: Cumulative LP | H1: Cumulative GP | I1: Net Cash Flow (for IRR)
A2: 1 | B2: 0 | C2: =B2-SUM('Capital Calls & Fees'!D2:D2) | D2: =MAX(0,C2*Assumptions!B5) | E2: =B2-D2 | F2: =D2 | G2: =SUM($E$2:E2) | H2: =SUM($F$2:F2) | I2: =-'Capital Calls & Fees'!B2+E2
A3: 2 | B3: 0 | C3: =B3-SUM('Capital Calls & Fees'!D2:D3) | D3: =MAX(0,C3*Assumptions!B5) | E3: =B3-D3 | F3: =D3 | G3: =SUM($E$2:E3) | H3: =SUM($F$2:F3) | I3: =-'Capital Calls & Fees'!B3+E3
A4: 3 | B4: 0 | C4: =B4-SUM('Capital Calls & Fees'!D2:D4) | D4: =MAX(0,C4*Assumptions!B5) | E4: =B4-D4 | F4: =D4 | G4: =SUM($E$2:E4) | H4: =SUM($F$2:F4) | I4: =-'Capital Calls & Fees'!B4+E4
A5: 4 | B5: 0 | C5: =B5-SUM('Capital Calls & Fees'!D2:D5) | D5: =MAX(0,C5*Assumptions!B5) | E5: =B5-D5 | F5: =D5 | G5: =SUM($E$2:E5) | H5: =SUM($F$2:F5) | I5: =-'Capital Calls & Fees'!B5+E5
A6: 5 | B6: 0 | C6: =B6-SUM('Capital Calls & Fees'!D2:D6) | D6: =MAX(0,C6*Assumptions!B5) | E6: =B6-D6 | F6: =D6 | G6: =SUM($E$2:E6) | H6: =SUM($F$2:F6) | I6: =-'Capital Calls & Fees'!B6+E6
A7: 6 | B7: =SUM('Capital Calls & Fees'!D2:D6)*Assumptions!B9*0.1 | C7: =B7-SUM('Capital Calls & Fees'!D2:D6) | D7: =MAX(0,C7*Assumptions!B5) | E7: =B7-D7 | F7: =D7 | G7: =SUM($E$2:E7) | H7: =SUM($F$2:F7) | I7: =-'Capital Calls & Fees'!B7+E7
A8: 7 | B8: =SUM('Capital Calls & Fees'!D2:D6)*Assumptions!B9*0.2 | C8: =B8-SUM('Capital Calls & Fees'!D2:D6) | D8: =MAX(0,C8*Assumptions!B5) | E8: =B8-D8 | F8: =D8 | G8: =SUM($E$2:E8) | H8: =SUM($F$2:F8) | I8: =-'Capital Calls & Fees'!B8+E8
A9: 8 | B9: =SUM('Capital Calls & Fees'!D2:D6)*Assumptions!B9*0.3 | C9: =B9-SUM('Capital Calls & Fees'!D2:D6) | D9: =MAX(0,C9*Assumptions!B5) | E9: =B9-D9 | F9: =D9 | G9: =SUM($E$2:E9) | H9: =SUM($F$2:F9) | I9: =-'Capital Calls & Fees'!B9+E9
A10: 9 | B10: =SUM('Capital Calls & Fees'!D2:D6)*Assumptions!B9*0.3 | C10: =B10-SUM('Capital Calls & Fees'!D2:D6) | D10: =MAX(0,C10*Assumptions!B5) | E10: =B10-D10 | F10: =D10 | G10: =SUM($E$2:E10) | H10: =SUM($F$2:F10) | I10: =-'Capital Calls & Fees'!B10+E10
A11: 10 | B11: =SUM('Capital Calls & Fees'!D2:D6)*Assumptions!B9*0.1 | C11: =B11-SUM('Capital Calls & Fees'!D2:D6) | D11: =MAX(0,C11*Assumptions!B5) | E11: =B11-D11 | F11: =D11 | G11: =SUM($E$2:E11) | H11: =SUM($F$2:F11) | I11: =-'Capital Calls & Fees'!B11+E11

Sheet KPI Summary Dashboard
A1: VC Fund Performance Dashboard
A3: Metric | B3: Value
A4: Total Paid-In Capital | B4: =SUM('Capital Calls & Fees'!B2:B11)
A5: Total Net Invested | B5: =SUM('Capital Calls & Fees'!D2:D11)
A6: Total Gross Proceeds | B6: =SUM('Distributions & Carry'!B2:B11)
A7: Total Distributions to LP | B7: =SUM('Distributions & Carry'!E2:E11)
A8: Total GP Carry | B8: =SUM('Distributions & Carry'!D2:D11)
A9: DPI (Distributed to Paid-In) | B9: =IF(B3=0,0,B6/B3)
A10: MOIC (Multiple on Invested Capital) | B10: =IF(B4=0,0,B5/B4)
A11: IRR (Internal Rate of Return) | B11: =IRR('Distributions & Carry'!I2:I11,0.1)
A12: GP % of Total Profit | B12: =IF((B6+B7)=0,0,B7/(B6+B7))
